yamlpp/__init__.py
yamlpp/__main__.py
yamlpp-1.0.1.dist-info/LICENSE
yamlpp-1.0.1.dist-info/METADATA
yamlpp-1.0.1.dist-info/WHEEL
yamlpp-1.0.1.dist-info/entry_points.txt
yamlpp-1.0.1.dist-info/top_level.txt
yamlpp-1.0.1.dist-info/RECORD
