Metadata-Version: 2.1
Name: yamlpp
Version: 1.0.1
Summary: Simple YAML preprocessor, resolves anchors.
Home-page: https://github.com/mrexodia/yamlpp
Author: Duncan Ogilvie
License: UNKNOWN
Platform: UNKNOWN
Classifier: Programming Language :: Python
Classifier: License :: OSI Approved :: MIT License
Classifier: Operating System :: OS Independent
Requires-Dist: ruamel.yaml
